test.py
test_multitask.py
ai_pentestsii/__init__.py
ai_pentestsii/begin.py
config/ai_config.py
prompts/prompt_v6.py
prompts/prompt_v6_simple.py
prompts/prompt_v7.py
prompts/prompt_v7_modif.py
prompts/prompt_v8.py
prompts/prompt_v8_modif.py
prompts/prompt_webpen_v1.py
tasks/install_util.py
tasks/report_creation.py
tasks/session_management.py
tasks/target_info.py
tasks/task_execution.py
tasks/utils.py
tasks/multitasking/multitask.py
tasks/multitasking/utils_multitask.py
ai_pentestsii-0.0.1.dist-info/LICENSE.txt
ai_pentestsii-0.0.1.dist-info/METADATA
ai_pentestsii-0.0.1.dist-info/WHEEL
ai_pentestsii-0.0.1.dist-info/entry_points.txt
ai_pentestsii-0.0.1.dist-info/top_level.txt
ai_pentestsii-0.0.1.dist-info/RECORD
